310-0.1.0.dist-info/DESCRIPTION.rst
310-0.1.0.dist-info/METADATA
310-0.1.0.dist-info/RECORD
310-0.1.0.dist-info/WHEEL
310-0.1.0.dist-info/metadata.json
310-0.1.0.dist-info/top_level.txt
extras/__init__.py
extras/divide.py
extras/multiply.py
